nexus_gateway/__init__.py
nexus_gateway/cli.py
nexus_gateway/client.py
nexus_gateway/preflight.py
nexus_gateway/test_nexus.py
nexus_gateway-3.1.3.dist-info/METADATA
nexus_gateway-3.1.3.dist-info/WHEEL
nexus_gateway-3.1.3.dist-info/entry_points.txt
nexus_gateway-3.1.3.dist-info/top_level.txt
nexus_gateway-3.1.3.dist-info/RECORD
