Metadata-Version: 2.4
Name: nexus_gateway
Version: 3.1.3
Summary: High-performance AI infrastructure with semantic caching and sovereign governance.
Home-page: https://nexus-gateway.org
Author: Sunny Anand
Author-email: asunny583@gmail.com
Classifier: Programming Language :: Python :: 3
Classifier: License :: OSI Approved :: MIT License
Classifier: Operating System :: OS Independent
Classifier: Topic :: Scientific/Engineering :: Artificial Intelligence
Classifier: Development Status :: 5 - Production/Stable
Requires-Python: >=3.7
Requires-Dist: requests>=2.25.0
Dynamic: author
Dynamic: author-email
Dynamic: classifier
Dynamic: description
Dynamic: description-content-type
Dynamic: home-page
Dynamic: requires-dist
Dynamic: requires-python
Dynamic: summary
